url_checks/__init__.py
url_checks/apps.py
url_checks/checks.py
url_checks/messages.py
url_checks/messages_text.py
django_url_checks-0.2.0.dist-info/LICENSE
django_url_checks-0.2.0.dist-info/WHEEL
django_url_checks-0.2.0.dist-info/METADATA
django_url_checks-0.2.0.dist-info/RECORD
