Metadata-Version: 2.1
Name: django-url-checks
Version: 0.2.0
Summary: Django checks to ensure valid URL Configurations
Home-page: https://github.com/jambonsw/django-url-checks
License: BSD-2-Clause
Keywords: django,check,url,uri,slash
Author: Andrew Pinkham
Author-email: code@andrewsforge.com
Requires-Python: >=3.6,<4.0
Classifier: Development Status :: 5 - Production/Stable
Classifier: Framework :: Django
Classifier: Framework :: Django :: 2.1
Classifier: Intended Audience :: Developers
Classifier: License :: OSI Approved :: BSD License
Classifier: Programming Language :: Python :: 3
Classifier: Programming Language :: Python :: 3.6
Classifier: Programming Language :: Python :: 3.7
Classifier: Topic :: Software Development :: Testing
Project-URL: Repository, https://github.com/jambonsw/django-url-checks
